pyodss/__init__.py
pyodss/__main__.py
pyodss/_version.py
pyodss/base.py
pyodss/config.py
pyodss-0.1a1.dist-info/LICENSE
pyodss-0.1a1.dist-info/METADATA
pyodss-0.1a1.dist-info/WHEEL
pyodss-0.1a1.dist-info/entry_points.txt
pyodss-0.1a1.dist-info/top_level.txt
pyodss-0.1a1.dist-info/RECORD
