Metadata-Version: 2.1
Name: pyodss
Version: 0.1a1
Summary: Python package for ODSS dataset
Author-email: Jonathan de Bruin <asreview@uu.nl>
License: MIT
Classifier: Development Status :: 5 - Production/Stable
Classifier: License :: OSI Approved :: MIT License
Classifier: Programming Language :: Python :: 3.6
Classifier: Programming Language :: Python :: 3.7
Classifier: Programming Language :: Python :: 3.8
Classifier: Programming Language :: Python :: 3.9
Classifier: Programming Language :: Python :: 3.10
Requires-Python: >=3.6
License-File: LICENSE
Requires-Dist: pyalex
Requires-Dist: tabulate
Provides-Extra: lint
Requires-Dist: flake8 ; extra == 'lint'
Requires-Dist: flake8-import-order ; extra == 'lint'
Provides-Extra: test
Requires-Dist: pytest ; extra == 'test'
